gse_utils/__init__.py
gse_utils/constants.py
gse_utils/detect_ports.py
gse_utils/detect_ports_linux.py
gse_utils/detect_ports_osx.py
gse_utils/detect_ports_windows.py
gse_utils/ser_driver.py
gse_utils/utils.py
gse_utils-2.7.0.dist-info/METADATA
gse_utils-2.7.0.dist-info/WHEEL
gse_utils-2.7.0.dist-info/licenses/LICENSE.md
gse_utils-2.7.0.dist-info/RECORD
