Metadata-Version: 2.4
Name: gse-utils
Version: 2.7.0
Summary: GSE utility functions
Author-email: Bogdan Marinescu <bogdan@gsat.us>
License-File: LICENSE.md
Requires-Python: >=3.8
Requires-Dist: colorama>=0.4.6
Requires-Dist: pyserial>=3.5
Requires-Dist: pyyaml>=6.0.2
